weaveapi/__init__.py
weaveapi/apicontext.py
weaveapi/clienthttp.py
weaveapi/clientws.py
weaveapi/filter.py
weaveapi/futures.py
weaveapi/javarandom.py
weaveapi/keys.py
weaveapi/nodeapi.py
weaveapi/options.py
weaveapi/records.py
weaveapi/session.py
weaveapi/setup.py
weaveapi/utils.py
weaveapi/weaveapi.py
weaveapi/weaveh.py
weave_py_api-1.2.8.dist-info/LICENSE
weave_py_api-1.2.8.dist-info/METADATA
weave_py_api-1.2.8.dist-info/WHEEL
weave_py_api-1.2.8.dist-info/top_level.txt
weave_py_api-1.2.8.dist-info/RECORD
