Metadata-Version: 2.1
Name: weave-py-api
Version: 1.2.8
Summary: Weavechain Python API
Author-email: Weavechain <support@weavechain.com>
License: MIT License
Project-URL: Homepage, https://github.com/weavechain/weave-py-api
Keywords: weavechain,weave,api,layer-0,data,sharing,monetization,compute,node
Classifier: License :: OSI Approved :: MIT License
Classifier: Programming Language :: Python
Classifier: Programming Language :: Python :: 3
Requires-Python: >=3.5
License-File: LICENSE
Requires-Dist: pathlib
Requires-Dist: requests
Requires-Dist: base58
Requires-Dist: pynacl
Requires-Dist: uuid
Requires-Dist: websocket-client
Requires-Dist: cryptography
Requires-Dist: PyCryptodome
Requires-Dist: paramiko
Requires-Dist: java-random
Requires-Dist: tomli ; python_version < "3.11"
Provides-Extra: dev
Requires-Dist: black ; extra == 'dev'
Requires-Dist: bumpver ; extra == 'dev'
Requires-Dist: isort ; extra == 'dev'
Requires-Dist: pip-tools ; extra == 'dev'
Requires-Dist: pytest ; extra == 'dev'
